msmb_theme/__init__.py
msmb_theme/_version.py
msmb_theme/breadcrumbs.html
msmb_theme/footer.html
msmb_theme/layout.html
msmb_theme/layout_old.html
msmb_theme/search.html
msmb_theme/searchbox.html
msmb_theme/theme.conf
msmb_theme/versions.html
msmb_theme/warning.html
msmb_theme/static/css/badge_only.css
msmb_theme/static/css/notebook-qual.css
msmb_theme/static/css/theme.css
msmb_theme/static/font/fontawesome_webfont.eot
msmb_theme/static/font/fontawesome_webfont.svg
msmb_theme/static/font/fontawesome_webfont.ttf
msmb_theme/static/font/fontawesome_webfont.woff
msmb_theme/static/js/theme.js
msmb_theme-0.3.1.dist-info/DESCRIPTION.rst
msmb_theme-0.3.1.dist-info/METADATA
msmb_theme-0.3.1.dist-info/metadata.json
msmb_theme-0.3.1.dist-info/RECORD
msmb_theme-0.3.1.dist-info/top_level.txt
msmb_theme-0.3.1.dist-info/WHEEL
